pyscard-2.3.0.dist-info/licenses/LICENSE
smartcard/ATR.py
smartcard/AbstractCardRequest.py
smartcard/Card.py
smartcard/CardConnection.py
smartcard/CardConnectionDecorator.py
smartcard/CardConnectionEvent.py
smartcard/CardConnectionObserver.py
smartcard/CardMonitoring.py
smartcard/CardRequest.py
smartcard/CardService.py
smartcard/CardType.py
smartcard/Exceptions.py
smartcard/ExclusiveConnectCardConnection.py
smartcard/ExclusiveTransmitCardConnection.py
smartcard/Observer.py
smartcard/PassThruCardService.py
smartcard/ReaderMonitoring.py
smartcard/Session.py
smartcard/Synchronization.py
smartcard/System.py
smartcard/__init__.py
smartcard/guid.py
smartcard/ulist.py
smartcard/pcsc/PCSCCardConnection.py
smartcard/pcsc/PCSCCardRequest.py
smartcard/pcsc/PCSCExceptions.py
smartcard/pcsc/PCSCPart10.py
smartcard/pcsc/PCSCReader.py
smartcard/pcsc/PCSCReaderGroups.py
smartcard/pcsc/__init__.py
smartcard/reader/Reader.py
smartcard/reader/ReaderFactory.py
smartcard/reader/ReaderGroups.py
smartcard/reader/__init__.py
smartcard/scard/__init__.py
smartcard/scard/_scard.cp311-win_amd64.pyd
smartcard/scard/scard.py
smartcard/sw/ErrorChecker.py
smartcard/sw/ErrorCheckingChain.py
smartcard/sw/ISO7816_4ErrorChecker.py
smartcard/sw/ISO7816_4_SW1ErrorChecker.py
smartcard/sw/ISO7816_8ErrorChecker.py
smartcard/sw/ISO7816_9ErrorChecker.py
smartcard/sw/SWExceptions.py
smartcard/sw/__init__.py
smartcard/sw/op21_ErrorChecker.py
smartcard/util/__init__.py
smartcard/wx/APDUHexValidator.py
smartcard/wx/APDUTracerPanel.py
smartcard/wx/CardAndReaderTreePanel.py
smartcard/wx/ReaderToolbar.py
smartcard/wx/SimpleSCardApp.py
smartcard/wx/SimpleSCardAppEventObserver.py
smartcard/wx/SimpleSCardAppFrame.py
smartcard/wx/__init__.py
smartcard/wx/resources/reader.ico
smartcard/wx/resources/smartcard.ico
pyscard-2.3.0.dist-info/METADATA
pyscard-2.3.0.dist-info/WHEEL
pyscard-2.3.0.dist-info/top_level.txt
pyscard-2.3.0.dist-info/RECORD
