Metadata-Version: 2.4
Name: pyscard
Version: 2.3.0
Summary: Smartcard module for Python.
Home-page: https://github.com/LudovicRousseau/pyscard
Download-URL: https://sourceforge.net/projects/pyscard/files/pyscard/pyscard%202.3.0/pyscard-2.3.0.tar.gz/download
Author: Ludovic Rousseau
Author-email: ludovic.rousseau@free.fr
Platform: linux
Platform: win32
Classifier: Development Status :: 5 - Production/Stable
Classifier: License :: OSI Approved :: GNU Lesser General Public License v2 or later (LGPLv2+)
Classifier: Intended Audience :: Developers
Classifier: Operating System :: Unix
Classifier: Operating System :: Microsoft :: Windows
Classifier: Operating System :: MacOS :: MacOS X
Classifier: Programming Language :: Python :: 3.9
Classifier: Programming Language :: Python :: 3.10
Classifier: Programming Language :: Python :: 3.11
Classifier: Programming Language :: Python :: 3.12
Classifier: Programming Language :: Python :: 3.13
Classifier: Topic :: Security
Requires-Python: >=3.9
License-File: LICENSE
Requires-Dist: typing_extensions; python_version == "3.9"
Provides-Extra: gui
Requires-Dist: wxPython; extra == "gui"
Dynamic: author
Dynamic: author-email
Dynamic: classifier
Dynamic: description
Dynamic: download-url
Dynamic: home-page
Dynamic: license-file
Dynamic: platform
Dynamic: provides-extra
Dynamic: requires-dist
Dynamic: requires-python
Dynamic: summary
